[
    {
        "id": 960802372,
        "type": "PushEvent",
        "actor": {
            "id": 15653088,
            "login": "meng1234qwert",
            "name": "mengzih",
            "avatar_url": "https://gitee.com/assets/no_portrait.png",
            "url": "https://gitee.com/api/v5/users/meng1234qwert",
            "html_url": "https://gitee.com/meng1234qwert",
            "remark": ""
        },
        "repo": {
            "id": 40341086,
            "full_name": "meng1234qwert/python2411",
            "human_name": "mengzih/python2411",
            "url": "https://gitee.com/api/v5/repos/meng1234qwert/python2411",
            "namespace": {
                "id": 14880996,
                "type": "personal",
                "name": "mengzih",
                "path": "meng1234qwert",
                "html_url": "https://gitee.com/meng1234qwert"
            }
        },
        "public": true,
        "created_at": "2025-04-09T21:40:06+08:00",
        "payload": {
            "ref": "refs/heads/master",
            "before": "669375db7181ec51d16bf1af830f7aece78b09de",
            "after": "e967ea64a62c4e7b9bac676f93e80e3bd5246873",
            "created": false,
            "deleted": false,
            "size": 1,
            "commits": [
                {
                    "sha": "e967ea64a62c4e7b9bac676f93e80e3bd5246873",
                    "author": {
                        "email": "2260234243@qq.com",
                        "name": "meng"
                    },
                    "message": "携程爬取（有问题）\n",
                    "url": "https://gitee.com/api/v5/repos/meng1234qwert/python2411/commits/e967ea64a62c4e7b9bac676f93e80e3bd5246873"
                }
            ]
        }
    },
    {
        "id": 960551434,
        "type": "PushEvent",
        "actor": {
            "id": 15653088,
            "login": "meng1234qwert",
            "name": "mengzih",
            "avatar_url": "https://gitee.com/assets/no_portrait.png",
            "url": "https://gitee.com/api/v5/users/meng1234qwert",
            "html_url": "https://gitee.com/meng1234qwert",
            "remark": ""
        },
        "repo": {
            "id": 40341086,
            "full_name": "meng1234qwert/python2411",
            "human_name": "mengzih/python2411",
            "url": "https://gitee.com/api/v5/repos/meng1234qwert/python2411",
            "namespace": {
                "id": 14880996,
                "type": "personal",
                "name": "mengzih",
                "path": "meng1234qwert",
                "html_url": "https://gitee.com/meng1234qwert"
            }
        },
        "public": true,
        "created_at": "2025-04-09T15:43:39+08:00",
        "payload": {
            "ref": "refs/heads/master",
            "before": "24b44730d1ac013d8f490a5434621a5cd2434188",
            "after": "669375db7181ec51d16bf1af830f7aece78b09de",
            "created": false,
            "deleted": false,
            "size": 1,
            "commits": [
                {
                    "sha": "669375db7181ec51d16bf1af830f7aece78b09de",
                    "author": {
                        "email": "2260234243@qq.com",
                        "name": "meng"
                    },
                    "message": "法院信息爬取\n",
                    "url": "https://gitee.com/api/v5/repos/meng1234qwert/python2411/commits/669375db7181ec51d16bf1af830f7aece78b09de"
                }
            ]
        }
    },
    {
        "id": 960166677,
        "type": "PushEvent",
        "actor": {
            "id": 15653088,
            "login": "meng1234qwert",
            "name": "mengzih",
            "avatar_url": "https://gitee.com/assets/no_portrait.png",
            "url": "https://gitee.com/api/v5/users/meng1234qwert",
            "html_url": "https://gitee.com/meng1234qwert",
            "remark": ""
        },
        "repo": {
            "id": 40341086,
            "full_name": "meng1234qwert/python2411",
            "human_name": "mengzih/python2411",
            "url": "https://gitee.com/api/v5/repos/meng1234qwert/python2411",
            "namespace": {
                "id": 14880996,
                "type": "personal",
                "name": "mengzih",
                "path": "meng1234qwert",
                "html_url": "https://gitee.com/meng1234qwert"
            }
        },
        "public": true,
        "created_at": "2025-04-08T21:27:06+08:00",
        "payload": {
            "ref": "refs/heads/master",
            "before": "9b232139e8a4c55e39830031966edd5c7dc3834c",
            "after": "24b44730d1ac013d8f490a5434621a5cd2434188",
            "created": false,
            "deleted": false,
            "size": 1,
            "commits": [
                {
                    "sha": "24b44730d1ac013d8f490a5434621a5cd2434188",
                    "author": {
                        "email": "2260234243@qq.com",
                        "name": "meng"
                    },
                    "message": "巅峰女生榜（小说内容未实现）\n",
                    "url": "https://gitee.com/api/v5/repos/meng1234qwert/python2411/commits/24b44730d1ac013d8f490a5434621a5cd2434188"
                }
            ]
        }
    },
    {
        "id": 960116310,
        "type": "PushEvent",
        "actor": {
            "id": 15653088,
            "login": "meng1234qwert",
            "name": "mengzih",
            "avatar_url": "https://gitee.com/assets/no_portrait.png",
            "url": "https://gitee.com/api/v5/users/meng1234qwert",
            "html_url": "https://gitee.com/meng1234qwert",
            "remark": ""
        },
        "repo": {
            "id": 40341086,
            "full_name": "meng1234qwert/python2411",
            "human_name": "mengzih/python2411",
            "url": "https://gitee.com/api/v5/repos/meng1234qwert/python2411",
            "namespace": {
                "id": 14880996,
                "type": "personal",
                "name": "mengzih",
                "path": "meng1234qwert",
                "html_url": "https://gitee.com/meng1234qwert"
            }
        },
        "public": true,
        "created_at": "2025-04-08T19:31:25+08:00",
        "payload": {
            "ref": "refs/heads/master",
            "before": "b506499a9ea9e846ebcf1551c57b27f152359afe",
            "after": "9b232139e8a4c55e39830031966edd5c7dc3834c",
            "created": false,
            "deleted": false,
            "size": 1,
            "commits": [
                {
                    "sha": "9b232139e8a4c55e39830031966edd5c7dc3834c",
                    "author": {
                        "email": "2260234243@qq.com",
                        "name": "meng"
                    },
                    "message": "bibi\n",
                    "url": "https://gitee.com/api/v5/repos/meng1234qwert/python2411/commits/9b232139e8a4c55e39830031966edd5c7dc3834c"
                }
            ]
        }
    },
    {
        "id": 959511065,
        "type": "PushEvent",
        "actor": {
            "id": 15653088,
            "login": "meng1234qwert",
            "name": "mengzih",
            "avatar_url": "https://gitee.com/assets/no_portrait.png",
            "url": "https://gitee.com/api/v5/users/meng1234qwert",
            "html_url": "https://gitee.com/meng1234qwert",
            "remark": ""
        },
        "repo": {
            "id": 40341086,
            "full_name": "meng1234qwert/python2411",
            "human_name": "mengzih/python2411",
            "url": "https://gitee.com/api/v5/repos/meng1234qwert/python2411",
            "namespace": {
                "id": 14880996,
                "type": "personal",
                "name": "mengzih",
                "path": "meng1234qwert",
                "html_url": "https://gitee.com/meng1234qwert"
            }
        },
        "public": true,
        "created_at": "2025-04-07T20:37:42+08:00",
        "payload": {
            "ref": "refs/heads/master",
            "before": "849a626f35f8ac7d114ee2e55332d5539009679d",
            "after": "b506499a9ea9e846ebcf1551c57b27f152359afe",
            "created": false,
            "deleted": false,
            "size": 1,
            "commits": [
                {
                    "sha": "b506499a9ea9e846ebcf1551c57b27f152359afe",
                    "author": {
                        "email": "2260234243@qq.com",
                        "name": "meng"
                    },
                    "message": "IP\n",
                    "url": "https://gitee.com/api/v5/repos/meng1234qwert/python2411/commits/b506499a9ea9e846ebcf1551c57b27f152359afe"
                }
            ]
        }
    },
    {
        "id": 959506462,
        "type": "PushEvent",
        "actor": {
            "id": 15653088,
            "login": "meng1234qwert",
            "name": "mengzih",
            "avatar_url": "https://gitee.com/assets/no_portrait.png",
            "url": "https://gitee.com/api/v5/users/meng1234qwert",
            "html_url": "https://gitee.com/meng1234qwert",
            "remark": ""
        },
        "repo": {
            "id": 40341086,
            "full_name": "meng1234qwert/python2411",
            "human_name": "mengzih/python2411",
            "url": "https://gitee.com/api/v5/repos/meng1234qwert/python2411",
            "namespace": {
                "id": 14880996,
                "type": "personal",
                "name": "mengzih",
                "path": "meng1234qwert",
                "html_url": "https://gitee.com/meng1234qwert"
            }
        },
        "public": true,
        "created_at": "2025-04-07T20:26:53+08:00",
        "payload": {
            "ref": "refs/heads/master",
            "before": "2316420a69f0a8b4d38c165402d83733616e4893",
            "after": "849a626f35f8ac7d114ee2e55332d5539009679d",
            "created": false,
            "deleted": false,
            "size": 1,
            "commits": [
                {
                    "sha": "849a626f35f8ac7d114ee2e55332d5539009679d",
                    "author": {
                        "email": "2260234243@qq.com",
                        "name": "meng"
                    },
                    "message": "央视网\n",
                    "url": "https://gitee.com/api/v5/repos/meng1234qwert/python2411/commits/849a626f35f8ac7d114ee2e55332d5539009679d"
                }
            ]
        }
    },
    {
        "id": 959192042,
        "type": "PushEvent",
        "actor": {
            "id": 15653088,
            "login": "meng1234qwert",
            "name": "mengzih",
            "avatar_url": "https://gitee.com/assets/no_portrait.png",
            "url": "https://gitee.com/api/v5/users/meng1234qwert",
            "html_url": "https://gitee.com/meng1234qwert",
            "remark": ""
        },
        "repo": {
            "id": 40341086,
            "full_name": "meng1234qwert/python2411",
            "human_name": "mengzih/python2411",
            "url": "https://gitee.com/api/v5/repos/meng1234qwert/python2411",
            "namespace": {
                "id": 14880996,
                "type": "personal",
                "name": "mengzih",
                "path": "meng1234qwert",
                "html_url": "https://gitee.com/meng1234qwert"
            }
        },
        "public": true,
        "created_at": "2025-04-07T13:51:56+08:00",
        "payload": {
            "ref": "refs/heads/master",
            "before": "5f49c70cf1c35776aab7f66a8eb39f449b4db789",
            "after": "2316420a69f0a8b4d38c165402d83733616e4893",
            "created": false,
            "deleted": false,
            "compare": "https://gitee.com/meng1234qwert/python2411/compare/5f49c70cf1c35776aab7f66a8eb39f449b4db789...2316420a69f0a8b4d38c165402d83733616e4893",
            "size": 2,
            "commits": [
                {
                    "sha": "eed0211c180b10a7fc83e6683d0e8c2523da2e33",
                    "author": {
                        "email": "2260234243@qq.com",
                        "name": "meng"
                    },
                    "message": "高校精选贴吧\n",
                    "url": "https://gitee.com/api/v5/repos/meng1234qwert/python2411/commits/eed0211c180b10a7fc83e6683d0e8c2523da2e33"
                },
                {
                    "sha": "2316420a69f0a8b4d38c165402d83733616e4893",
                    "author": {
                        "email": "2260234243@qq.com",
                        "name": "meng"
                    },
                    "message": "pymongo\n",
                    "url": "https://gitee.com/api/v5/repos/meng1234qwert/python2411/commits/2316420a69f0a8b4d38c165402d83733616e4893"
                }
            ]
        }
    },
    {
        "id": 957772881,
        "type": "PushEvent",
        "actor": {
            "id": 15653088,
            "login": "meng1234qwert",
            "name": "mengzih",
            "avatar_url": "https://gitee.com/assets/no_portrait.png",
            "url": "https://gitee.com/api/v5/users/meng1234qwert",
            "html_url": "https://gitee.com/meng1234qwert",
            "remark": ""
        },
        "repo": {
            "id": 40341086,
            "full_name": "meng1234qwert/python2411",
            "human_name": "mengzih/python2411",
            "url": "https://gitee.com/api/v5/repos/meng1234qwert/python2411",
            "namespace": {
                "id": 14880996,
                "type": "personal",
                "name": "mengzih",
                "path": "meng1234qwert",
                "html_url": "https://gitee.com/meng1234qwert"
            }
        },
        "public": true,
        "created_at": "2025-04-02T20:23:06+08:00",
        "payload": {
            "ref": "refs/heads/master",
            "before": "40f68d59f7d265368cee2259e1aecca836101f1c",
            "after": "5f49c70cf1c35776aab7f66a8eb39f449b4db789",
            "created": false,
            "deleted": false,
            "size": 1,
            "commits": [
                {
                    "sha": "5f49c70cf1c35776aab7f66a8eb39f449b4db789",
                    "author": {
                        "email": "2260234243@qq.com",
                        "name": "meng"
                    },
                    "message": "模拟登录二种管理Cookie的方法\n",
                    "url": "https://gitee.com/api/v5/repos/meng1234qwert/python2411/commits/5f49c70cf1c35776aab7f66a8eb39f449b4db789"
                }
            ]
        }
    },
    {
        "id": 957448108,
        "type": "PushEvent",
        "actor": {
            "id": 15653088,
            "login": "meng1234qwert",
            "name": "mengzih",
            "avatar_url": "https://gitee.com/assets/no_portrait.png",
            "url": "https://gitee.com/api/v5/users/meng1234qwert",
            "html_url": "https://gitee.com/meng1234qwert",
            "remark": ""
        },
        "repo": {
            "id": 40341086,
            "full_name": "meng1234qwert/python2411",
            "human_name": "mengzih/python2411",
            "url": "https://gitee.com/api/v5/repos/meng1234qwert/python2411",
            "namespace": {
                "id": 14880996,
                "type": "personal",
                "name": "mengzih",
                "path": "meng1234qwert",
                "html_url": "https://gitee.com/meng1234qwert"
            }
        },
        "public": true,
        "created_at": "2025-04-02T13:50:34+08:00",
        "payload": {
            "ref": "refs/heads/master",
            "before": "5a24b3dca181942a08f7cdbd531be5b9cb7654d1",
            "after": "40f68d59f7d265368cee2259e1aecca836101f1c",
            "created": false,
            "deleted": false,
            "size": 1,
            "commits": [
                {
                    "sha": "40f68d59f7d265368cee2259e1aecca836101f1c",
                    "author": {
                        "email": "2260234243@qq.com",
                        "name": "meng"
                    },
                    "message": "爬虫网站\n",
                    "url": "https://gitee.com/api/v5/repos/meng1234qwert/python2411/commits/40f68d59f7d265368cee2259e1aecca836101f1c"
                }
            ]
        }
    },
    {
        "id": 957175216,
        "type": "PushEvent",
        "actor": {
            "id": 15653088,
            "login": "meng1234qwert",
            "name": "mengzih",
            "avatar_url": "https://gitee.com/assets/no_portrait.png",
            "url": "https://gitee.com/api/v5/users/meng1234qwert",
            "html_url": "https://gitee.com/meng1234qwert",
            "remark": ""
        },
        "repo": {
            "id": 40341086,
            "full_name": "meng1234qwert/python2411",
            "human_name": "mengzih/python2411",
            "url": "https://gitee.com/api/v5/repos/meng1234qwert/python2411",
            "namespace": {
                "id": 14880996,
                "type": "personal",
                "name": "mengzih",
                "path": "meng1234qwert",
                "html_url": "https://gitee.com/meng1234qwert"
            }
        },
        "public": true,
        "created_at": "2025-04-01T21:40:35+08:00",
        "payload": {
            "ref": "refs/heads/master",
            "before": "425614337dd330de8e606c0be3ab7a2930315102",
            "after": "5a24b3dca181942a08f7cdbd531be5b9cb7654d1",
            "created": false,
            "deleted": false,
            "size": 1,
            "commits": [
                {
                    "sha": "5a24b3dca181942a08f7cdbd531be5b9cb7654d1",
                    "author": {
                        "email": "2260234243@qq.com",
                        "name": "meng"
                    },
                    "message": "爬取网页图片\n",
                    "url": "https://gitee.com/api/v5/repos/meng1234qwert/python2411/commits/5a24b3dca181942a08f7cdbd531be5b9cb7654d1"
                }
            ]
        }
    },
    {
        "id": 957131879,
        "type": "PushEvent",
        "actor": {
            "id": 15653088,
            "login": "meng1234qwert",
            "name": "mengzih",
            "avatar_url": "https://gitee.com/assets/no_portrait.png",
            "url": "https://gitee.com/api/v5/users/meng1234qwert",
            "html_url": "https://gitee.com/meng1234qwert",
            "remark": ""
        },
        "repo": {
            "id": 40341086,
            "full_name": "meng1234qwert/python2411",
            "human_name": "mengzih/python2411",
            "url": "https://gitee.com/api/v5/repos/meng1234qwert/python2411",
            "namespace": {
                "id": 14880996,
                "type": "personal",
                "name": "mengzih",
                "path": "meng1234qwert",
                "html_url": "https://gitee.com/meng1234qwert"
            }
        },
        "public": true,
        "created_at": "2025-04-01T20:00:54+08:00",
        "payload": {
            "ref": "refs/heads/master",
            "before": "8f8d34eeff03b74a9f8db5b5155ba37413e2fd8a",
            "after": "425614337dd330de8e606c0be3ab7a2930315102",
            "created": false,
            "deleted": false,
            "size": 1,
            "commits": [
                {
                    "sha": "425614337dd330de8e606c0be3ab7a2930315102",
                    "author": {
                        "email": "2260234243@qq.com",
                        "name": "meng"
                    },
                    "message": "爬取上个网页的三种图片已经完成\n",
                    "url": "https://gitee.com/api/v5/repos/meng1234qwert/python2411/commits/425614337dd330de8e606c0be3ab7a2930315102"
                }
            ]
        }
    },
    {
        "id": 957106698,
        "type": "PushEvent",
        "actor": {
            "id": 15653088,
            "login": "meng1234qwert",
            "name": "mengzih",
            "avatar_url": "https://gitee.com/assets/no_portrait.png",
            "url": "https://gitee.com/api/v5/users/meng1234qwert",
            "html_url": "https://gitee.com/meng1234qwert",
            "remark": ""
        },
        "repo": {
            "id": 40341086,
            "full_name": "meng1234qwert/python2411",
            "human_name": "mengzih/python2411",
            "url": "https://gitee.com/api/v5/repos/meng1234qwert/python2411",
            "namespace": {
                "id": 14880996,
                "type": "personal",
                "name": "mengzih",
                "path": "meng1234qwert",
                "html_url": "https://gitee.com/meng1234qwert"
            }
        },
        "public": true,
        "created_at": "2025-04-01T19:07:08+08:00",
        "payload": {
            "ref": "refs/heads/master",
            "before": "27017a4036331f24327a34494d7e0165843eb2c6",
            "after": "8f8d34eeff03b74a9f8db5b5155ba37413e2fd8a",
            "created": false,
            "deleted": false,
            "size": 1,
            "commits": [
                {
                    "sha": "8f8d34eeff03b74a9f8db5b5155ba37413e2fd8a",
                    "author": {
                        "email": "2260234243@qq.com",
                        "name": "meng"
                    },
                    "message": "基础知识梳理\n",
                    "url": "https://gitee.com/api/v5/repos/meng1234qwert/python2411/commits/8f8d34eeff03b74a9f8db5b5155ba37413e2fd8a"
                }
            ]
        }
    },
    {
        "id": 956612541,
        "type": "PushEvent",
        "actor": {
            "id": 15653088,
            "login": "meng1234qwert",
            "name": "mengzih",
            "avatar_url": "https://gitee.com/assets/no_portrait.png",
            "url": "https://gitee.com/api/v5/users/meng1234qwert",
            "html_url": "https://gitee.com/meng1234qwert",
            "remark": ""
        },
        "repo": {
            "id": 40341086,
            "full_name": "meng1234qwert/python2411",
            "human_name": "mengzih/python2411",
            "url": "https://gitee.com/api/v5/repos/meng1234qwert/python2411",
            "namespace": {
                "id": 14880996,
                "type": "personal",
                "name": "mengzih",
                "path": "meng1234qwert",
                "html_url": "https://gitee.com/meng1234qwert"
            }
        },
        "public": true,
        "created_at": "2025-04-01T08:56:42+08:00",
        "payload": {
            "ref": "refs/heads/master",
            "before": "d990304413ad874e66be1cf9376816be659b8bb7",
            "after": "27017a4036331f24327a34494d7e0165843eb2c6",
            "created": false,
            "deleted": false,
            "size": 1,
            "commits": [
                {
                    "sha": "27017a4036331f24327a34494d7e0165843eb2c6",
                    "author": {
                        "email": "2260234243@qq.com",
                        "name": "meng"
                    },
                    "message": "失败版本三连击\n",
                    "url": "https://gitee.com/api/v5/repos/meng1234qwert/python2411/commits/27017a4036331f24327a34494d7e0165843eb2c6"
                }
            ]
        }
    },
    {
        "id": 956138153,
        "type": "CreateEvent",
        "actor": {
            "id": 15653088,
            "login": "meng1234qwert",
            "name": "mengzih",
            "avatar_url": "https://gitee.com/assets/no_portrait.png",
            "url": "https://gitee.com/api/v5/users/meng1234qwert",
            "html_url": "https://gitee.com/meng1234qwert",
            "remark": ""
        },
        "repo": {
            "id": 40341086,
            "full_name": "meng1234qwert/python2411",
            "human_name": "mengzih/python2411",
            "url": "https://gitee.com/api/v5/repos/meng1234qwert/python2411",
            "namespace": {
                "id": 14880996,
                "type": "personal",
                "name": "mengzih",
                "path": "meng1234qwert",
                "html_url": "https://gitee.com/meng1234qwert"
            }
        },
        "public": true,
        "created_at": "2025-03-31T12:36:00+08:00",
        "payload": {
            "ref_type": "branch",
            "ref": "master",
            "default_branch": "master",
            "description": ""
        }
    },
    {
        "id": 956135521,
        "type": "CreateEvent",
        "actor": {
            "id": 15653088,
            "login": "meng1234qwert",
            "name": "mengzih",
            "avatar_url": "https://gitee.com/assets/no_portrait.png",
            "url": "https://gitee.com/api/v5/users/meng1234qwert",
            "html_url": "https://gitee.com/meng1234qwert",
            "remark": ""
        },
        "repo": {
            "id": 40341086,
            "full_name": "meng1234qwert/python2411",
            "human_name": "mengzih/python2411",
            "url": "https://gitee.com/api/v5/repos/meng1234qwert/python2411",
            "namespace": {
                "id": 14880996,
                "type": "personal",
                "name": "mengzih",
                "path": "meng1234qwert",
                "html_url": "https://gitee.com/meng1234qwert"
            }
        },
        "public": true,
        "created_at": "2025-03-31T12:29:08+08:00",
        "payload": {
            "ref_type": "repository",
            "ref": null,
            "default_branch": "master",
            "description": ""
        }
    }
]