[
    {
        "id": 964575513,
        "type": "PushEvent",
        "actor": {
            "id": 15653054,
            "login": "lets-explode-reality",
            "name": "爆发吧现实",
            "avatar_url": "https://gitee.com/assets/no_portrait.png",
            "url": "https://gitee.com/api/v5/users/lets-explode-reality",
            "html_url": "https://gitee.com/lets-explode-reality",
            "remark": ""
        },
        "repo": {
            "id": 40340109,
            "full_name": "lets-explode-reality/python2411",
            "human_name": "爆发吧现实/mypython2411",
            "url": "https://gitee.com/api/v5/repos/lets-explode-reality/python2411",
            "namespace": {
                "id": 14880958,
                "type": "personal",
                "name": "爆发吧现实",
                "path": "lets-explode-reality",
                "html_url": "https://gitee.com/lets-explode-reality"
            }
        },
        "public": true,
        "created_at": "2025-04-16T21:04:35+08:00",
        "payload": {
            "ref": "refs/heads/master",
            "before": "9185c4634d277b1fa3194e54d4e3b161bbb7fc2a",
            "after": "d44a0e683cd3563559ae3cee459ada77a6415cbc",
            "created": false,
            "deleted": false,
            "size": 1,
            "commits": [
                {
                    "sha": "d44a0e683cd3563559ae3cee459ada77a6415cbc",
                    "author": {
                        "email": "2839611825@qq.com",
                        "name": "wangdi"
                    },
                    "message": "巨潮资讯\n",
                    "url": "https://gitee.com/api/v5/repos/lets-explode-reality/python2411/commits/d44a0e683cd3563559ae3cee459ada77a6415cbc"
                }
            ]
        }
    },
    {
        "id": 964555254,
        "type": "PushEvent",
        "actor": {
            "id": 15653054,
            "login": "lets-explode-reality",
            "name": "爆发吧现实",
            "avatar_url": "https://gitee.com/assets/no_portrait.png",
            "url": "https://gitee.com/api/v5/users/lets-explode-reality",
            "html_url": "https://gitee.com/lets-explode-reality",
            "remark": ""
        },
        "repo": {
            "id": 40340109,
            "full_name": "lets-explode-reality/python2411",
            "human_name": "爆发吧现实/mypython2411",
            "url": "https://gitee.com/api/v5/repos/lets-explode-reality/python2411",
            "namespace": {
                "id": 14880958,
                "type": "personal",
                "name": "爆发吧现实",
                "path": "lets-explode-reality",
                "html_url": "https://gitee.com/lets-explode-reality"
            }
        },
        "public": true,
        "created_at": "2025-04-16T20:12:38+08:00",
        "payload": {
            "ref": "refs/heads/master",
            "before": "3c1cdf56f62b296e2e55fbd780cf4fbe89504ff1",
            "after": "9185c4634d277b1fa3194e54d4e3b161bbb7fc2a",
            "created": false,
            "deleted": false,
            "size": 1,
            "commits": [
                {
                    "sha": "9185c4634d277b1fa3194e54d4e3b161bbb7fc2a",
                    "author": {
                        "email": "2839611825@qq.com",
                        "name": "wangdi"
                    },
                    "message": "扩展\n",
                    "url": "https://gitee.com/api/v5/repos/lets-explode-reality/python2411/commits/9185c4634d277b1fa3194e54d4e3b161bbb7fc2a"
                }
            ]
        }
    },
    {
        "id": 964012624,
        "type": "PushEvent",
        "actor": {
            "id": 15653054,
            "login": "lets-explode-reality",
            "name": "爆发吧现实",
            "avatar_url": "https://gitee.com/assets/no_portrait.png",
            "url": "https://gitee.com/api/v5/users/lets-explode-reality",
            "html_url": "https://gitee.com/lets-explode-reality",
            "remark": ""
        },
        "repo": {
            "id": 40340109,
            "full_name": "lets-explode-reality/python2411",
            "human_name": "爆发吧现实/mypython2411",
            "url": "https://gitee.com/api/v5/repos/lets-explode-reality/python2411",
            "namespace": {
                "id": 14880958,
                "type": "personal",
                "name": "爆发吧现实",
                "path": "lets-explode-reality",
                "html_url": "https://gitee.com/lets-explode-reality"
            }
        },
        "public": true,
        "created_at": "2025-04-16T08:51:59+08:00",
        "payload": {
            "ref": "refs/heads/master",
            "before": "a439ecdabdda10e536aa0884ee2c00830f8e2d04",
            "after": "3c1cdf56f62b296e2e55fbd780cf4fbe89504ff1",
            "created": false,
            "deleted": false,
            "size": 1,
            "commits": [
                {
                    "sha": "3c1cdf56f62b296e2e55fbd780cf4fbe89504ff1",
                    "author": {
                        "email": "2839611825@qq.com",
                        "name": "wangdi"
                    },
                    "message": "深度爬虫债券\n",
                    "url": "https://gitee.com/api/v5/repos/lets-explode-reality/python2411/commits/3c1cdf56f62b296e2e55fbd780cf4fbe89504ff1"
                }
            ]
        }
    },
    {
        "id": 963393349,
        "type": "PushEvent",
        "actor": {
            "id": 15653054,
            "login": "lets-explode-reality",
            "name": "爆发吧现实",
            "avatar_url": "https://gitee.com/assets/no_portrait.png",
            "url": "https://gitee.com/api/v5/users/lets-explode-reality",
            "html_url": "https://gitee.com/lets-explode-reality",
            "remark": ""
        },
        "repo": {
            "id": 40340109,
            "full_name": "lets-explode-reality/python2411",
            "human_name": "爆发吧现实/mypython2411",
            "url": "https://gitee.com/api/v5/repos/lets-explode-reality/python2411",
            "namespace": {
                "id": 14880958,
                "type": "personal",
                "name": "爆发吧现实",
                "path": "lets-explode-reality",
                "html_url": "https://gitee.com/lets-explode-reality"
            }
        },
        "public": true,
        "created_at": "2025-04-15T09:55:12+08:00",
        "payload": {
            "ref": "refs/heads/master",
            "before": "0dfc3b5e266ae3cdf7abf495db0682d1e627afdb",
            "after": "a439ecdabdda10e536aa0884ee2c00830f8e2d04",
            "created": false,
            "deleted": false,
            "size": 1,
            "commits": [
                {
                    "sha": "a439ecdabdda10e536aa0884ee2c00830f8e2d04",
                    "author": {
                        "email": "2839611825@qq.com",
                        "name": "wangdi"
                    },
                    "message": "面向对象\n",
                    "url": "https://gitee.com/api/v5/repos/lets-explode-reality/python2411/commits/a439ecdabdda10e536aa0884ee2c00830f8e2d04"
                }
            ]
        }
    },
    {
        "id": 963352221,
        "type": "PushEvent",
        "actor": {
            "id": 15653054,
            "login": "lets-explode-reality",
            "name": "爆发吧现实",
            "avatar_url": "https://gitee.com/assets/no_portrait.png",
            "url": "https://gitee.com/api/v5/users/lets-explode-reality",
            "html_url": "https://gitee.com/lets-explode-reality",
            "remark": ""
        },
        "repo": {
            "id": 40340109,
            "full_name": "lets-explode-reality/python2411",
            "human_name": "爆发吧现实/mypython2411",
            "url": "https://gitee.com/api/v5/repos/lets-explode-reality/python2411",
            "namespace": {
                "id": 14880958,
                "type": "personal",
                "name": "爆发吧现实",
                "path": "lets-explode-reality",
                "html_url": "https://gitee.com/lets-explode-reality"
            }
        },
        "public": true,
        "created_at": "2025-04-15T08:57:56+08:00",
        "payload": {
            "ref": "refs/heads/master",
            "before": "ddb24b6639e8149d31c0a18cf2db066575a7f94e",
            "after": "0dfc3b5e266ae3cdf7abf495db0682d1e627afdb",
            "created": false,
            "deleted": false,
            "size": 1,
            "commits": [
                {
                    "sha": "0dfc3b5e266ae3cdf7abf495db0682d1e627afdb",
                    "author": {
                        "email": "2839611825@qq.com",
                        "name": "wangdi"
                    },
                    "message": "Bilibili\n",
                    "url": "https://gitee.com/api/v5/repos/lets-explode-reality/python2411/commits/0dfc3b5e266ae3cdf7abf495db0682d1e627afdb"
                }
            ]
        }
    },
    {
        "id": 963350171,
        "type": "PushEvent",
        "actor": {
            "id": 15653054,
            "login": "lets-explode-reality",
            "name": "爆发吧现实",
            "avatar_url": "https://gitee.com/assets/no_portrait.png",
            "url": "https://gitee.com/api/v5/users/lets-explode-reality",
            "html_url": "https://gitee.com/lets-explode-reality",
            "remark": ""
        },
        "repo": {
            "id": 40340109,
            "full_name": "lets-explode-reality/python2411",
            "human_name": "爆发吧现实/mypython2411",
            "url": "https://gitee.com/api/v5/repos/lets-explode-reality/python2411",
            "namespace": {
                "id": 14880958,
                "type": "personal",
                "name": "爆发吧现实",
                "path": "lets-explode-reality",
                "html_url": "https://gitee.com/lets-explode-reality"
            }
        },
        "public": true,
        "created_at": "2025-04-15T08:52:24+08:00",
        "payload": {
            "ref": "refs/heads/master",
            "before": "0a24a0fca462644f6c47227165ad684489f1cbf9",
            "after": "ddb24b6639e8149d31c0a18cf2db066575a7f94e",
            "created": false,
            "deleted": false,
            "size": 1,
            "commits": [
                {
                    "sha": "ddb24b6639e8149d31c0a18cf2db066575a7f94e",
                    "author": {
                        "email": "2839611825@qq.com",
                        "name": "wangdi"
                    },
                    "message": "去重\n",
                    "url": "https://gitee.com/api/v5/repos/lets-explode-reality/python2411/commits/ddb24b6639e8149d31c0a18cf2db066575a7f94e"
                }
            ]
        }
    },
    {
        "id": 963350038,
        "type": "PushEvent",
        "actor": {
            "id": 15653054,
            "login": "lets-explode-reality",
            "name": "爆发吧现实",
            "avatar_url": "https://gitee.com/assets/no_portrait.png",
            "url": "https://gitee.com/api/v5/users/lets-explode-reality",
            "html_url": "https://gitee.com/lets-explode-reality",
            "remark": ""
        },
        "repo": {
            "id": 40340109,
            "full_name": "lets-explode-reality/python2411",
            "human_name": "爆发吧现实/mypython2411",
            "url": "https://gitee.com/api/v5/repos/lets-explode-reality/python2411",
            "namespace": {
                "id": 14880958,
                "type": "personal",
                "name": "爆发吧现实",
                "path": "lets-explode-reality",
                "html_url": "https://gitee.com/lets-explode-reality"
            }
        },
        "public": true,
        "created_at": "2025-04-15T08:52:01+08:00",
        "payload": {
            "ref": "refs/heads/master",
            "before": "9d3e3af9e465ec35da5f2a4544618627d2560830",
            "after": "0a24a0fca462644f6c47227165ad684489f1cbf9",
            "created": false,
            "deleted": false,
            "size": 1,
            "commits": [
                {
                    "sha": "0a24a0fca462644f6c47227165ad684489f1cbf9",
                    "author": {
                        "email": "2839611825@qq.com",
                        "name": "wangdi"
                    },
                    "message": "扩展\n",
                    "url": "https://gitee.com/api/v5/repos/lets-explode-reality/python2411/commits/0a24a0fca462644f6c47227165ad684489f1cbf9"
                }
            ]
        }
    },
    {
        "id": 963349908,
        "type": "PushEvent",
        "actor": {
            "id": 15653054,
            "login": "lets-explode-reality",
            "name": "爆发吧现实",
            "avatar_url": "https://gitee.com/assets/no_portrait.png",
            "url": "https://gitee.com/api/v5/users/lets-explode-reality",
            "html_url": "https://gitee.com/lets-explode-reality",
            "remark": ""
        },
        "repo": {
            "id": 40340109,
            "full_name": "lets-explode-reality/python2411",
            "human_name": "爆发吧现实/mypython2411",
            "url": "https://gitee.com/api/v5/repos/lets-explode-reality/python2411",
            "namespace": {
                "id": 14880958,
                "type": "personal",
                "name": "爆发吧现实",
                "path": "lets-explode-reality",
                "html_url": "https://gitee.com/lets-explode-reality"
            }
        },
        "public": true,
        "created_at": "2025-04-15T08:51:30+08:00",
        "payload": {
            "ref": "refs/heads/master",
            "before": "887c0a5cc81265a1943c1e092e30cedd60e7c87e",
            "after": "9d3e3af9e465ec35da5f2a4544618627d2560830",
            "created": false,
            "deleted": false,
            "size": 1,
            "commits": [
                {
                    "sha": "9d3e3af9e465ec35da5f2a4544618627d2560830",
                    "author": {
                        "email": "2839611825@qq.com",
                        "name": "wangdi"
                    },
                    "message": "练习\n",
                    "url": "https://gitee.com/api/v5/repos/lets-explode-reality/python2411/commits/9d3e3af9e465ec35da5f2a4544618627d2560830"
                }
            ]
        }
    },
    {
        "id": 963089646,
        "type": "PushEvent",
        "actor": {
            "id": 15653054,
            "login": "lets-explode-reality",
            "name": "爆发吧现实",
            "avatar_url": "https://gitee.com/assets/no_portrait.png",
            "url": "https://gitee.com/api/v5/users/lets-explode-reality",
            "html_url": "https://gitee.com/lets-explode-reality",
            "remark": ""
        },
        "repo": {
            "id": 40340109,
            "full_name": "lets-explode-reality/python2411",
            "human_name": "爆发吧现实/mypython2411",
            "url": "https://gitee.com/api/v5/repos/lets-explode-reality/python2411",
            "namespace": {
                "id": 14880958,
                "type": "personal",
                "name": "爆发吧现实",
                "path": "lets-explode-reality",
                "html_url": "https://gitee.com/lets-explode-reality"
            }
        },
        "public": true,
        "created_at": "2025-04-14T16:58:54+08:00",
        "payload": {
            "ref": "refs/heads/master",
            "before": "32a5f2fcf01fff326ba5101c797ee45cfdf907fc",
            "after": "887c0a5cc81265a1943c1e092e30cedd60e7c87e",
            "created": false,
            "deleted": false,
            "size": 1,
            "commits": [
                {
                    "sha": "887c0a5cc81265a1943c1e092e30cedd60e7c87e",
                    "author": {
                        "email": "2839611825@qq.com",
                        "name": "wangdi"
                    },
                    "message": "scrapy\n",
                    "url": "https://gitee.com/api/v5/repos/lets-explode-reality/python2411/commits/887c0a5cc81265a1943c1e092e30cedd60e7c87e"
                }
            ]
        }
    },
    {
        "id": 963088609,
        "type": "PushEvent",
        "actor": {
            "id": 15653054,
            "login": "lets-explode-reality",
            "name": "爆发吧现实",
            "avatar_url": "https://gitee.com/assets/no_portrait.png",
            "url": "https://gitee.com/api/v5/users/lets-explode-reality",
            "html_url": "https://gitee.com/lets-explode-reality",
            "remark": ""
        },
        "repo": {
            "id": 40340109,
            "full_name": "lets-explode-reality/python2411",
            "human_name": "爆发吧现实/mypython2411",
            "url": "https://gitee.com/api/v5/repos/lets-explode-reality/python2411",
            "namespace": {
                "id": 14880958,
                "type": "personal",
                "name": "爆发吧现实",
                "path": "lets-explode-reality",
                "html_url": "https://gitee.com/lets-explode-reality"
            }
        },
        "public": true,
        "created_at": "2025-04-14T16:57:55+08:00",
        "payload": {
            "ref": "refs/heads/master",
            "before": "b7c61b405089145d40585c5fd3252f4b6aee9f20",
            "after": "32a5f2fcf01fff326ba5101c797ee45cfdf907fc",
            "created": false,
            "deleted": false,
            "size": 1,
            "commits": [
                {
                    "sha": "32a5f2fcf01fff326ba5101c797ee45cfdf907fc",
                    "author": {
                        "email": "2839611825@qq.com",
                        "name": "wangdi"
                    },
                    "message": "scrapy\n",
                    "url": "https://gitee.com/api/v5/repos/lets-explode-reality/python2411/commits/32a5f2fcf01fff326ba5101c797ee45cfdf907fc"
                }
            ]
        }
    },
    {
        "id": 961451759,
        "type": "PushEvent",
        "actor": {
            "id": 15653054,
            "login": "lets-explode-reality",
            "name": "爆发吧现实",
            "avatar_url": "https://gitee.com/assets/no_portrait.png",
            "url": "https://gitee.com/api/v5/users/lets-explode-reality",
            "html_url": "https://gitee.com/lets-explode-reality",
            "remark": ""
        },
        "repo": {
            "id": 40340109,
            "full_name": "lets-explode-reality/python2411",
            "human_name": "爆发吧现实/mypython2411",
            "url": "https://gitee.com/api/v5/repos/lets-explode-reality/python2411",
            "namespace": {
                "id": 14880958,
                "type": "personal",
                "name": "爆发吧现实",
                "path": "lets-explode-reality",
                "html_url": "https://gitee.com/lets-explode-reality"
            }
        },
        "public": true,
        "created_at": "2025-04-10T21:45:16+08:00",
        "payload": {
            "ref": "refs/heads/master",
            "before": "32780a13fbc4a8ff0d4fd732e08ca89489fae87e",
            "after": "b7c61b405089145d40585c5fd3252f4b6aee9f20",
            "created": false,
            "deleted": false,
            "size": 1,
            "commits": [
                {
                    "sha": "b7c61b405089145d40585c5fd3252f4b6aee9f20",
                    "author": {
                        "email": "2839611825@qq.com",
                        "name": "wangdi"
                    },
                    "message": "樱花\n",
                    "url": "https://gitee.com/api/v5/repos/lets-explode-reality/python2411/commits/b7c61b405089145d40585c5fd3252f4b6aee9f20"
                }
            ]
        }
    },
    {
        "id": 961442063,
        "type": "PushEvent",
        "actor": {
            "id": 15653054,
            "login": "lets-explode-reality",
            "name": "爆发吧现实",
            "avatar_url": "https://gitee.com/assets/no_portrait.png",
            "url": "https://gitee.com/api/v5/users/lets-explode-reality",
            "html_url": "https://gitee.com/lets-explode-reality",
            "remark": ""
        },
        "repo": {
            "id": 40340109,
            "full_name": "lets-explode-reality/python2411",
            "human_name": "爆发吧现实/mypython2411",
            "url": "https://gitee.com/api/v5/repos/lets-explode-reality/python2411",
            "namespace": {
                "id": 14880958,
                "type": "personal",
                "name": "爆发吧现实",
                "path": "lets-explode-reality",
                "html_url": "https://gitee.com/lets-explode-reality"
            }
        },
        "public": true,
        "created_at": "2025-04-10T21:22:17+08:00",
        "payload": {
            "ref": "refs/heads/master",
            "before": "f26d691b658f298e4c172bc66fbd3b4ff27e0eb8",
            "after": "32780a13fbc4a8ff0d4fd732e08ca89489fae87e",
            "created": false,
            "deleted": false,
            "size": 1,
            "commits": [
                {
                    "sha": "32780a13fbc4a8ff0d4fd732e08ca89489fae87e",
                    "author": {
                        "email": "2839611825@qq.com",
                        "name": "wangdi"
                    },
                    "message": "线程协程\n",
                    "url": "https://gitee.com/api/v5/repos/lets-explode-reality/python2411/commits/32780a13fbc4a8ff0d4fd732e08ca89489fae87e"
                }
            ]
        }
    },
    {
        "id": 961414044,
        "type": "PushEvent",
        "actor": {
            "id": 15653054,
            "login": "lets-explode-reality",
            "name": "爆发吧现实",
            "avatar_url": "https://gitee.com/assets/no_portrait.png",
            "url": "https://gitee.com/api/v5/users/lets-explode-reality",
            "html_url": "https://gitee.com/lets-explode-reality",
            "remark": ""
        },
        "repo": {
            "id": 40340109,
            "full_name": "lets-explode-reality/python2411",
            "human_name": "爆发吧现实/mypython2411",
            "url": "https://gitee.com/api/v5/repos/lets-explode-reality/python2411",
            "namespace": {
                "id": 14880958,
                "type": "personal",
                "name": "爆发吧现实",
                "path": "lets-explode-reality",
                "html_url": "https://gitee.com/lets-explode-reality"
            }
        },
        "public": true,
        "created_at": "2025-04-10T20:13:41+08:00",
        "payload": {
            "ref": "refs/heads/master",
            "before": "f96df0cc22d24a3defefcfad3c9ac93ad98504bc",
            "after": "f26d691b658f298e4c172bc66fbd3b4ff27e0eb8",
            "created": false,
            "deleted": false,
            "compare": "https://gitee.com/lets-explode-reality/python2411/compare/f96df0cc22d24a3defefcfad3c9ac93ad98504bc...f26d691b658f298e4c172bc66fbd3b4ff27e0eb8",
            "size": 4,
            "commits": [
                {
                    "sha": "59e95b5b97b1b8e3eca8820ab2b7d2d26f08478e",
                    "author": {
                        "email": "2839611825@qq.com",
                        "name": "wangdi"
                    },
                    "message": "地方债\n",
                    "url": "https://gitee.com/api/v5/repos/lets-explode-reality/python2411/commits/59e95b5b97b1b8e3eca8820ab2b7d2d26f08478e"
                },
                {
                    "sha": "d6700b2d8e73a4763fa9fbf3122602d35c3bc063",
                    "author": {
                        "email": "2839611825@qq.com",
                        "name": "wangdi"
                    },
                    "message": "require\n",
                    "url": "https://gitee.com/api/v5/repos/lets-explode-reality/python2411/commits/d6700b2d8e73a4763fa9fbf3122602d35c3bc063"
                },
                {
                    "sha": "f90bf93b47bbfe71131506f2635866527f9f94b5",
                    "author": {
                        "email": "2839611825@qq.com",
                        "name": "wangdi"
                    },
                    "message": "bs4\n",
                    "url": "https://gitee.com/api/v5/repos/lets-explode-reality/python2411/commits/f90bf93b47bbfe71131506f2635866527f9f94b5"
                },
                {
                    "sha": "f26d691b658f298e4c172bc66fbd3b4ff27e0eb8",
                    "author": {
                        "email": "2839611825@qq.com",
                        "name": "wangdi"
                    },
                    "message": "4/10\n",
                    "url": "https://gitee.com/api/v5/repos/lets-explode-reality/python2411/commits/f26d691b658f298e4c172bc66fbd3b4ff27e0eb8"
                }
            ]
        }
    },
    {
        "id": 960801022,
        "type": "PushEvent",
        "actor": {
            "id": 15653054,
            "login": "lets-explode-reality",
            "name": "爆发吧现实",
            "avatar_url": "https://gitee.com/assets/no_portrait.png",
            "url": "https://gitee.com/api/v5/users/lets-explode-reality",
            "html_url": "https://gitee.com/lets-explode-reality",
            "remark": ""
        },
        "repo": {
            "id": 40340109,
            "full_name": "lets-explode-reality/python2411",
            "human_name": "爆发吧现实/mypython2411",
            "url": "https://gitee.com/api/v5/repos/lets-explode-reality/python2411",
            "namespace": {
                "id": 14880958,
                "type": "personal",
                "name": "爆发吧现实",
                "path": "lets-explode-reality",
                "html_url": "https://gitee.com/lets-explode-reality"
            }
        },
        "public": true,
        "created_at": "2025-04-09T21:36:25+08:00",
        "payload": {
            "ref": "refs/heads/master",
            "before": "b0946ee1d746c3f3e3417f019a63c13d2339648f",
            "after": "f96df0cc22d24a3defefcfad3c9ac93ad98504bc",
            "created": false,
            "deleted": false,
            "size": 1,
            "commits": [
                {
                    "sha": "f96df0cc22d24a3defefcfad3c9ac93ad98504bc",
                    "author": {
                        "email": "2839611825@qq.com",
                        "name": "wangdi"
                    },
                    "message": "4.9\n",
                    "url": "https://gitee.com/api/v5/repos/lets-explode-reality/python2411/commits/f96df0cc22d24a3defefcfad3c9ac93ad98504bc"
                }
            ]
        }
    },
    {
        "id": 960800831,
        "type": "PushEvent",
        "actor": {
            "id": 15653054,
            "login": "lets-explode-reality",
            "name": "爆发吧现实",
            "avatar_url": "https://gitee.com/assets/no_portrait.png",
            "url": "https://gitee.com/api/v5/users/lets-explode-reality",
            "html_url": "https://gitee.com/lets-explode-reality",
            "remark": ""
        },
        "repo": {
            "id": 40340109,
            "full_name": "lets-explode-reality/python2411",
            "human_name": "爆发吧现实/mypython2411",
            "url": "https://gitee.com/api/v5/repos/lets-explode-reality/python2411",
            "namespace": {
                "id": 14880958,
                "type": "personal",
                "name": "爆发吧现实",
                "path": "lets-explode-reality",
                "html_url": "https://gitee.com/lets-explode-reality"
            }
        },
        "public": true,
        "created_at": "2025-04-09T21:35:46+08:00",
        "payload": {
            "ref": "refs/heads/master",
            "before": "9b08cd4e326d1ffa7eb0c351460157392a626fa7",
            "after": "b0946ee1d746c3f3e3417f019a63c13d2339648f",
            "created": false,
            "deleted": false,
            "size": 1,
            "commits": [
                {
                    "sha": "b0946ee1d746c3f3e3417f019a63c13d2339648f",
                    "author": {
                        "email": "2839611825@qq.com",
                        "name": "wangdi"
                    },
                    "message": "协程\n",
                    "url": "https://gitee.com/api/v5/repos/lets-explode-reality/python2411/commits/b0946ee1d746c3f3e3417f019a63c13d2339648f"
                }
            ]
        }
    },
    {
        "id": 960173223,
        "type": "PushEvent",
        "actor": {
            "id": 15653054,
            "login": "lets-explode-reality",
            "name": "爆发吧现实",
            "avatar_url": "https://gitee.com/assets/no_portrait.png",
            "url": "https://gitee.com/api/v5/users/lets-explode-reality",
            "html_url": "https://gitee.com/lets-explode-reality",
            "remark": ""
        },
        "repo": {
            "id": 40340109,
            "full_name": "lets-explode-reality/python2411",
            "human_name": "爆发吧现实/mypython2411",
            "url": "https://gitee.com/api/v5/repos/lets-explode-reality/python2411",
            "namespace": {
                "id": 14880958,
                "type": "personal",
                "name": "爆发吧现实",
                "path": "lets-explode-reality",
                "html_url": "https://gitee.com/lets-explode-reality"
            }
        },
        "public": true,
        "created_at": "2025-04-08T21:42:50+08:00",
        "payload": {
            "ref": "refs/heads/master",
            "before": "2ca6c6a37af8c31073832012e9159058ce5047b3",
            "after": "9b08cd4e326d1ffa7eb0c351460157392a626fa7",
            "created": false,
            "deleted": false,
            "size": 1,
            "commits": [
                {
                    "sha": "9b08cd4e326d1ffa7eb0c351460157392a626fa7",
                    "author": {
                        "email": "2839611825@qq.com",
                        "name": "wangdi"
                    },
                    "message": "4.8\n",
                    "url": "https://gitee.com/api/v5/repos/lets-explode-reality/python2411/commits/9b08cd4e326d1ffa7eb0c351460157392a626fa7"
                }
            ]
        }
    },
    {
        "id": 960172526,
        "type": "PushEvent",
        "actor": {
            "id": 15653054,
            "login": "lets-explode-reality",
            "name": "爆发吧现实",
            "avatar_url": "https://gitee.com/assets/no_portrait.png",
            "url": "https://gitee.com/api/v5/users/lets-explode-reality",
            "html_url": "https://gitee.com/lets-explode-reality",
            "remark": ""
        },
        "repo": {
            "id": 40340109,
            "full_name": "lets-explode-reality/python2411",
            "human_name": "爆发吧现实/mypython2411",
            "url": "https://gitee.com/api/v5/repos/lets-explode-reality/python2411",
            "namespace": {
                "id": 14880958,
                "type": "personal",
                "name": "爆发吧现实",
                "path": "lets-explode-reality",
                "html_url": "https://gitee.com/lets-explode-reality"
            }
        },
        "public": true,
        "created_at": "2025-04-08T21:41:04+08:00",
        "payload": {
            "ref": "refs/heads/master",
            "before": "284a2750c3549a6287d3646b374ceb0903f4e3c7",
            "after": "2ca6c6a37af8c31073832012e9159058ce5047b3",
            "created": false,
            "deleted": false,
            "size": 1,
            "commits": [
                {
                    "sha": "2ca6c6a37af8c31073832012e9159058ce5047b3",
                    "author": {
                        "email": "2839611825@qq.com",
                        "name": "wangdi"
                    },
                    "message": "gite\n",
                    "url": "https://gitee.com/api/v5/repos/lets-explode-reality/python2411/commits/2ca6c6a37af8c31073832012e9159058ce5047b3"
                }
            ]
        }
    },
    {
        "id": 960095157,
        "type": "PushEvent",
        "actor": {
            "id": 15653054,
            "login": "lets-explode-reality",
            "name": "爆发吧现实",
            "avatar_url": "https://gitee.com/assets/no_portrait.png",
            "url": "https://gitee.com/api/v5/users/lets-explode-reality",
            "html_url": "https://gitee.com/lets-explode-reality",
            "remark": ""
        },
        "repo": {
            "id": 40340109,
            "full_name": "lets-explode-reality/python2411",
            "human_name": "爆发吧现实/mypython2411",
            "url": "https://gitee.com/api/v5/repos/lets-explode-reality/python2411",
            "namespace": {
                "id": 14880958,
                "type": "personal",
                "name": "爆发吧现实",
                "path": "lets-explode-reality",
                "html_url": "https://gitee.com/lets-explode-reality"
            }
        },
        "public": true,
        "created_at": "2025-04-08T18:47:15+08:00",
        "payload": {
            "ref": "refs/heads/master",
            "before": "7727211f9dbd04d7bb0d21b6ecdf95dcc3cb2186",
            "after": "284a2750c3549a6287d3646b374ceb0903f4e3c7",
            "created": false,
            "deleted": false,
            "size": 1,
            "commits": [
                {
                    "sha": "284a2750c3549a6287d3646b374ceb0903f4e3c7",
                    "author": {
                        "email": "2839611825@qq.com",
                        "name": "wangdi"
                    },
                    "message": "热门番剧\n",
                    "url": "https://gitee.com/api/v5/repos/lets-explode-reality/python2411/commits/284a2750c3549a6287d3646b374ceb0903f4e3c7"
                }
            ]
        }
    },
    {
        "id": 959917515,
        "type": "PushEvent",
        "actor": {
            "id": 15653054,
            "login": "lets-explode-reality",
            "name": "爆发吧现实",
            "avatar_url": "https://gitee.com/assets/no_portrait.png",
            "url": "https://gitee.com/api/v5/users/lets-explode-reality",
            "html_url": "https://gitee.com/lets-explode-reality",
            "remark": ""
        },
        "repo": {
            "id": 40340109,
            "full_name": "lets-explode-reality/python2411",
            "human_name": "爆发吧现实/mypython2411",
            "url": "https://gitee.com/api/v5/repos/lets-explode-reality/python2411",
            "namespace": {
                "id": 14880958,
                "type": "personal",
                "name": "爆发吧现实",
                "path": "lets-explode-reality",
                "html_url": "https://gitee.com/lets-explode-reality"
            }
        },
        "public": true,
        "created_at": "2025-04-08T15:43:24+08:00",
        "payload": {
            "ref": "refs/heads/master",
            "before": "f657e4530970acd153ac706a53183f328061210a",
            "after": "7727211f9dbd04d7bb0d21b6ecdf95dcc3cb2186",
            "created": false,
            "deleted": false,
            "size": 1,
            "commits": [
                {
                    "sha": "7727211f9dbd04d7bb0d21b6ecdf95dcc3cb2186",
                    "author": {
                        "email": "2839611825@qq.com",
                        "name": "wangdi"
                    },
                    "message": "隧道代理爬取top250\n",
                    "url": "https://gitee.com/api/v5/repos/lets-explode-reality/python2411/commits/7727211f9dbd04d7bb0d21b6ecdf95dcc3cb2186"
                }
            ]
        }
    },
    {
        "id": 959862960,
        "type": "PushEvent",
        "actor": {
            "id": 15653054,
            "login": "lets-explode-reality",
            "name": "爆发吧现实",
            "avatar_url": "https://gitee.com/assets/no_portrait.png",
            "url": "https://gitee.com/api/v5/users/lets-explode-reality",
            "html_url": "https://gitee.com/lets-explode-reality",
            "remark": ""
        },
        "repo": {
            "id": 40340109,
            "full_name": "lets-explode-reality/python2411",
            "human_name": "爆发吧现实/mypython2411",
            "url": "https://gitee.com/api/v5/repos/lets-explode-reality/python2411",
            "namespace": {
                "id": 14880958,
                "type": "personal",
                "name": "爆发吧现实",
                "path": "lets-explode-reality",
                "html_url": "https://gitee.com/lets-explode-reality"
            }
        },
        "public": true,
        "created_at": "2025-04-08T14:49:50+08:00",
        "payload": {
            "ref": "refs/heads/master",
            "before": "5c85ceb7e14b4af920f45e38b0eff348464c81b7",
            "after": "f657e4530970acd153ac706a53183f328061210a",
            "created": false,
            "deleted": false,
            "size": 1,
            "commits": [
                {
                    "sha": "f657e4530970acd153ac706a53183f328061210a",
                    "author": {
                        "email": "2839611825@qq.com",
                        "name": "wangdi"
                    },
                    "message": "豆瓣top250爬与反爬\n",
                    "url": "https://gitee.com/api/v5/repos/lets-explode-reality/python2411/commits/f657e4530970acd153ac706a53183f328061210a"
                }
            ]
        }
    }
]